uffutils/__init__.py
uffutils/__main__.py
uffutils/cli.py
uffutils/file.py
uffutils/view.py
uffutils/uff/__init__.py
uffutils/uff/dataset.py
uffutils/uff/subsetmap.py
uffutils/uff/uffdata.py
uffutils-0.3.0.dist-info/METADATA
uffutils-0.3.0.dist-info/WHEEL
uffutils-0.3.0.dist-info/entry_points.txt
uffutils-0.3.0.dist-info/RECORD
