Metadata-Version: 2.4
Name: uffutils
Version: 0.3.0
Summary: A set of commandline tools for manipulating UFF files.
Author-email: Jan Hein de Jong <janhein.dejong@gmail.com>
Requires-Python: >=3.13
Requires-Dist: click<9.0.0,>=8.1.8
Requires-Dist: pyuff<3.0.0,>=2.4.6
